LICENSE
MANIFEST.in
README.md
requirements.txt
setup.py
Py_redis_ratelimit.egg-info/PKG-INFO
Py_redis_ratelimit.egg-info/SOURCES.txt
Py_redis_ratelimit.egg-info/dependency_links.txt
Py_redis_ratelimit.egg-info/requires.txt
Py_redis_ratelimit.egg-info/top_level.txt
ratelimit/__init__.py