Metadata-Version: 2.1
Name: Py-redis-ratelimit
Version: 0.1.2
Summary: A simple asyncio-based rate limiter for Python3 using Redis.
Home-page: https://github.com/AYMENJD/py-redis-ratelimit
Author: AYMEN Mohammed
Author-email: let.me.code.safe@gmail.com
License: MIT
Project-URL: Source, https://github.com/AYMENJD/py-redis-ratelimit
Project-URL: Tracker, https://github.com/AYMENJD/py-redis-ratelimit/issues
Keywords: ratelimit,redis,flood,spam,asyncio
Requires-Python: >=3.7
License-File: LICENSE
